myRoot/__init__.py
myRoot/myRoot.py
myRoot-0.0.7.dist-info/METADATA
myRoot-0.0.7.dist-info/WHEEL
myRoot-0.0.7.dist-info/top_level.txt
myRoot-0.0.7.dist-info/RECORD
