Metadata-Version: 2.1
Name: myRoot
Version: 0.0.7
Summary: Librería para setear rutas raiz en subcarpetas de forma simple y minimalista.
Home-page: https://github.com/YzackZack476
Author: Corona C. Issac
Author-email: issaccoronacordoba@gmail.com
License: PUBLIC
Platform: UNKNOWN
